ai_alignment/__init__.py
ai_alignment-0.0.1.dist-info/METADATA
ai_alignment-0.0.1.dist-info/WHEEL
ai_alignment-0.0.1.dist-info/RECORD
