Metadata-Version: 2.4
Name: ai-alignment
Version: 0.0.1
Summary: Whitecircle.ai utilities for aligning model behavior with stated policies.
Author: White Circle
License: MIT
Keywords: ai,alignment,guardrails,policy,safety,whitecircle.ai
Classifier: Development Status :: 3 - Alpha
Classifier: License :: OSI Approved :: MIT License
Classifier: Programming Language :: Python :: 3
Requires-Python: >=3.9
